kmodels/__init__.py
kmodels/error.py
kmodels/types.py
kmodels/models/__init__.py
kmodels/models/coremodel/__init__.py
kmodels/models/coremodel/coremodel.py
kmodels/test/__init__.py
kmodels/test/test.py
kmodels/utils/__init__.py
kmodels/utils/abstract_utils.py
kmodels/utils/literal_utils.py
kmodels/utils/union_utils.py
kmodels-0.1.3.1.dist-info/licenses/LICENSE
kmodels-0.1.3.1.dist-info/METADATA
kmodels-0.1.3.1.dist-info/WHEEL
kmodels-0.1.3.1.dist-info/top_level.txt
kmodels-0.1.3.1.dist-info/RECORD
