Metadata-Version: 2.4
Name: kmodels
Version: 0.1.3.1
Summary: KModels
Home-page: https://github.com/kokaito-git/kmodels
Author: kokaito-git
Author-email: kokaito.git@gmail.com
Classifier: Programming Language :: Python :: 3
Classifier: Operating System :: OS Independent
Classifier: Operating System :: Microsoft :: Windows
Classifier: Operating System :: MacOS
Classifier: Operating System :: POSIX :: Linux
Classifier: License :: OSI Approved :: MIT License
Requires-Python: >=3.13
License-File: LICENSE
Requires-Dist: pydantic
Requires-Dist: typeguard
Requires-Dist: kcolors
Dynamic: author
Dynamic: author-email
Dynamic: classifier
Dynamic: home-page
Dynamic: license-file
Dynamic: requires-dist
Dynamic: requires-python
Dynamic: summary
